llama_parse/__init__.py
llama_parse/base.py
llama_parse/utils.py
llama_parse/cli/__init__.py
llama_parse/cli/main.py
llama_parse-0.6.91.dist-info/METADATA
llama_parse-0.6.91.dist-info/WHEEL
llama_parse-0.6.91.dist-info/entry_points.txt
llama_parse-0.6.91.dist-info/RECORD
